cdk_managed_ad/__init__.py
cdk_managed_ad/py.typed
cdk_managed_ad/_jsii/__init__.py
cdk_managed_ad/_jsii/cdk-managed-ad@0.0.20.jsii.tgz
cdk_managed_ad-0.0.20.dist-info/LICENSE
cdk_managed_ad-0.0.20.dist-info/METADATA
cdk_managed_ad-0.0.20.dist-info/WHEEL
cdk_managed_ad-0.0.20.dist-info/top_level.txt
cdk_managed_ad-0.0.20.dist-info/RECORD
